kubespawner/__init__.py
kubespawner/_version.py
kubespawner/clients.py
kubespawner/objects.py
kubespawner/proxy.py
kubespawner/reflector.py
kubespawner/slugs.py
kubespawner/spawner.py
kubespawner/utils.py
kubespawner/templates/form.html
kubespawner/templates/style.css
jupyterhub_kubespawner-7.0.0.dist-info/METADATA
jupyterhub_kubespawner-7.0.0.dist-info/WHEEL
jupyterhub_kubespawner-7.0.0.dist-info/licenses/LICENSE
jupyterhub_kubespawner-7.0.0.dist-info/RECORD
