Metadata-Version: 2.3
Name: jupyterhub-kubespawner
Version: 7.0.0
Summary: JupyterHub Spawner for Kubernetes
Project-URL: Documentation, https://jupyterhub-kubespawner.readthedocs.io
Project-URL: Source, https://github.com/jupyterhub/kubespawner
Project-URL: Issues, https://github.com/jupyterhub/kubespawner/issues
Author-email: Jupyter Contributors <jupyter@googlegroups.com>
License: BSD 3-Clause License
License-File: LICENSE
Keywords: jupyterhub,spawner
Classifier: Development Status :: 5 - Production/Stable
Classifier: Programming Language :: Python :: 3
Requires-Python: >=3.7
Requires-Dist: escapism
Requires-Dist: jinja2
Requires-Dist: jupyterhub>=4.0.0
Requires-Dist: kubernetes-asyncio>=24.2.3
Requires-Dist: python-slugify
Requires-Dist: pyyaml
Requires-Dist: traitlets
Requires-Dist: urllib3
Provides-Extra: test
Requires-Dist: kubernetes>=11; extra == 'test'
Requires-Dist: pytest-asyncio<0.23,>=0.17; extra == 'test'
Requires-Dist: pytest-cov; extra == 'test'
Requires-Dist: pytest>=5.4; extra == 'test'
